datasette_sqlite_http/__init__.py
datasette_sqlite_http/version.py
datasette_sqlite_http-0.1.1.dist-info/METADATA
datasette_sqlite_http-0.1.1.dist-info/WHEEL
datasette_sqlite_http-0.1.1.dist-info/entry_points.txt
datasette_sqlite_http-0.1.1.dist-info/top_level.txt
datasette_sqlite_http-0.1.1.dist-info/RECORD
