Metadata-Version: 2.1
Name: datasette-sqlite-http
Version: 0.1.1
Home-page: https://github.com/asg017/sqlite-http
Author: Alex Garcia
License: MIT License, Apache License, Version 2.0
Project-URL: Issues, https://github.com/asg017/sqlite-http/issues
Project-URL: CI, https://github.com/asg017/sqlite-http/actions
Project-URL: Changelog, https://github.com/asg017/sqlite-http/releases
Requires-Python: >=3.7
Requires-Dist: datasette
Requires-Dist: sqlite-http
Provides-Extra: test
Requires-Dist: pytest ; extra == 'test'
